setup.py
django_write_around_cache/__init__.py
django_write_around_cache/utils.py
django_write_around_cache/view_mixins.py
django_write_around_cache.egg-info/PKG-INFO
django_write_around_cache.egg-info/SOURCES.txt
django_write_around_cache.egg-info/dependency_links.txt
django_write_around_cache.egg-info/requires.txt
django_write_around_cache.egg-info/top_level.txt
django_write_around_cache/templatetags/__init__.py
django_write_around_cache/templatetags/write_around_cache.py