Metadata-Version: 1.0
Name: django-write-around-cache
Version: 0.3.0
Summary: Override Django's template cache at will
Home-page: https://github.com/gizmag/django-write-around-cache
Author: Gizmag
Author-email: tech@gizmag.com
License: UNKNOWN
Platform: UNKNOWN
